quizlet_sets/__init__.py
quizlet_sets/export.py
quizlet_sets/set_class.py
quizlet_sets/sets.py
quizlet_sets-0.0.2.dist-info/LICENSE
quizlet_sets-0.0.2.dist-info/METADATA
quizlet_sets-0.0.2.dist-info/WHEEL
quizlet_sets-0.0.2.dist-info/top_level.txt
quizlet_sets-0.0.2.dist-info/RECORD
