Metadata-Version: 2.1
Name: quizlet-sets
Version: 0.0.2
Summary: A package to download Quizlet study sets
Home-page: https://github.com/ashton0223/quizlet-sets
Author: Ashton South
Author-email: aasouth223@gmail.com
License: UNKNOWN
Project-URL: Bug Tracker, https://github.com/ashton0223/quizlet-sets/issues
Platform: UNKNOWN
Classifier: Programming Language :: Python :: 3
Classifier: License :: OSI Approved :: MIT License
Classifier: Operating System :: OS Independent
Requires-Python: >=3.6
License-File: LICENSE
Requires-Dist: genanki
Requires-Dist: xlwt
Requires-Dist: beautifulsoup4
